Rydberg_EIT_Calculator/__init__.py
Rydberg_EIT_Calculator-0.0.2.dist-info/LICENSE.rtf
Rydberg_EIT_Calculator-0.0.2.dist-info/METADATA
Rydberg_EIT_Calculator-0.0.2.dist-info/WHEEL
Rydberg_EIT_Calculator-0.0.2.dist-info/top_level.txt
Rydberg_EIT_Calculator-0.0.2.dist-info/RECORD
