Metadata-Version: 2.1
Name: Rydberg-EIT-Calculator
Version: 0.0.2
Summary: A EIT Response Calculator
Home-page: https://github.com/Einspiao/EIT-Calculator
Author: Shengpu_Wang
Author-email: harrywang1126@outlook.com
License: MIT
Platform: UNKNOWN
Requires-Python: >=3.8
License-File: LICENSE.rtf
